realestatescrape/__init__.py
real_estate_scrape-0.2.1.dist-info/METADATA
real_estate_scrape-0.2.1.dist-info/WHEEL
real_estate_scrape-0.2.1.dist-info/entry_points.txt
real_estate_scrape-0.2.1.dist-info/top_level.txt
real_estate_scrape-0.2.1.dist-info/RECORD
