Metadata-Version: 2.4
Name: real-estate-scrape
Version: 0.2.1
Summary: Get the estimated value of a property from Redfin and Zillow
Author-email: Mike Lee Williams <mike@mike.place>
License: MIT
Project-URL: Homepage, https://github.com/mikepqr/real-estate-scrape
Project-URL: Bug Reports, https://github.com/mikepqr/real-estate-scrape/issues
Project-URL: Source, https://github.com/mikepqr/real-estate-scrape
Keywords: twitter
Classifier: Development Status :: 4 - Beta
Classifier: Environment :: Console
Classifier: Intended Audience :: End Users/Desktop
Classifier: Topic :: Utilities
Classifier: License :: OSI Approved :: MIT License
Classifier: Programming Language :: Python :: 3
Classifier: Programming Language :: Python :: 3.7
Classifier: Programming Language :: Python :: 3.8
Classifier: Programming Language :: Python :: 3.9
Classifier: Programming Language :: Python :: 3.10
Classifier: Programming Language :: Python :: 3 :: Only
Requires-Python: >=3.7
Requires-Dist: lxml
Requires-Dist: matplotlib
Requires-Dist: pandas
Requires-Dist: pre-commit>=2.21.0
Requires-Dist: requests
